lab6Comb-backup.v
/*******************************************************************************/
/*Program Name: lab6Comb.v */
/*Description: Verilog description and test bench for a combinational circuit*/
/*Author: Eithne Amos */
/*Person number: 50209909 */
/*Date of completion: 12/8/2017 */
/*******************************************************************************/
module f_comb(a, b, c, f);
//inputs
input a, b, c;
//outputs
output f;
wire b_n, c_n, d_n, x_1, x_2, x_3, or_1;
//primitives
not(b_n, b);
not(c_n, c);
not(d_n, d);
xor(x_1, a, b_n);
xor(x_2, b, c_n);
xor(x_3, c, d_n);
or(or_1, x_1, x_2);
or(f, or_1, x_3);
endmodule

//testbench
module test_f;
reg t_a, t_b, t_c;
wire t_f;
f_comb in1(t_a, t_b, t_c, t_f);
initial
begin
t_a = 0; t_b = 0; t_c = 0;
#20
t_c = 1; 
#20
t_b = 1; t_c = 0;
#20
t_c = 1;
#20
t_a = 1; t_b = 0; t_c = 0;
#20
t_c = 1;
#20
t_b = 1; t_c = 0;
#20
t_c = 1;
end

// produce file
initial 
begin
$dumpfile("lab6Comb.vcd");
$dumpvars(0, test_f);
$monitor("inputs: a = %b, b = %b, c = %b | outputs: f = %b", t_a, t_b, t_c, t_f);
end
endmodule

lab6Comb.vcd
$date
	Fri Dec  8 18:02:19 2017
$end
$version
	Icarus Verilog
$end
$timescale
	1s
$end
$scope module test_f $end
$var wire 1 ! t_f $end
$var reg 1 " t_a $end
$var reg 1 # t_b $end
$var reg 1 $ t_c $end
$scope module in1 $end
$var wire 1 % a $end
$var wire 1 & b $end
$var wire 1 ' b_n $end
$var wire 1 ( c $end
$var wire 1 ) c_n $end
$var wire 1 * d $end
$var wire 1 + d_n $end
$var wire 1 ! f $end
$var wire 1 , or_1 $end
$var wire 1 - x_1 $end
$var wire 1 . x_2 $end
$var wire 1 / x_3 $end
$upscope $end
$upscope $end
$enddefinitions $end
#0
$dumpvars
x/
1.
1-
1,
x+
z*
1)
0(
1'
0&
0%
0$
0#
0"
1!
$end
#20
0.
0)
1$
1(
#40
x!
0,
0-
1)
0'
0.
0$
0(
1#
1&
#60
1!
1,
1.
0)
1$
1(
#80
1)
1'
1.
0-
0$
0(
0#
0&
1"
1%
#100
x!
0,
0.
0)
1$
1(
#120
1!
1-
1,
1)
0'
0.
0$
0(
1#
1&
#140
1.
0)
1$
1(
