lab6Seq.v
/*******************************************************************************/
/*Program Name: lab6Seq.v */
/*Description: Verilog description and test bench for a combinational circuit*/
/*Author: Eithne Amos */
/*Person number: 50209909 */
/*Date of completion: 12/8/2017 */
/*******************************************************************************/

module seq(x, clk, reset, out);
input x, clk, reset;
output reg out;
reg [2:0] state;

parameter s0=3'b000,
	  s1=3'b001,
	  s2=3'b010,
	  s3=3'b011,
	  s4=4'b100;

always @(posedge reset or posedge clk)
	if (reset) begin state = s0; end
	else
		case (state)
			s0: begin out=0;
				if (x) state = s4; 
				else state = s1; 
			end

			s1: begin out=0;
				if (x) state = s2;
				else state = s1;
			end

			s2: begin out = 1; 
				if (x) state = s4;
				else state = s3;
			end

			s3: begin out = 1;
				if (x) state = s2;
				else state = s1;
			end

			s4: begin out = 0;
				if (x) state = s4;
				else state = s3;
			end
		endcase

endmodule

module test;
reg t_x, t_clk, t_reset;
wire t_out;

seq in1(t_x, t_clk, t_reset, t_out);

initial begin
	t_x = 0;
	t_clk = 0;
	t_reset = 1;
	#10 t_reset = 0;


	repeat (32) begin
		t_x = ~t_x;
		#10 t_clk=~t_clk;
		#10 t_clk=~t_clk;
	end
		
		

end

// produce file
initial 
begin
$dumpfile("test.vcd");
$dumpvars(0, test);
$monitor("x: %b out: %b", t_x, t_out);
end
endmodule

test.vcd
$date
	Fri Dec  8 18:03:47 2017
$end
$version
	Icarus Verilog
$end
$timescale
	1s
$end
$scope module test $end
$var wire 1 ! t_out $end
$var reg 1 " t_clk $end
$var reg 1 # t_reset $end
$var reg 1 $ t_x $end
$scope module in1 $end
$var wire 1 % clk $end
$var wire 1 & reset $end
$var wire 1 ' x $end
$var reg 1 ( out $end
$var reg 3 ) state [2:0] $end
$upscope $end
$upscope $end
$enddefinitions $end
#0
$dumpvars
b0 )
x(
0'
1&
0%
0$
1#
0"
x!
$end
#10
1$
1'
0#
0&
#20
b100 )
0(
0!
1"
1%
#30
0$
0'
0"
0%
#40
b11 )
1"
1%
#50
1$
1'
0"
0%
#60
b10 )
1(
1!
1"
1%
#70
0$
0'
0"
0%
#80
b11 )
1"
1%
#90
1$
1'
0"
0%
#100
b10 )
1"
1%
#110
0$
0'
0"
0%
#120
b11 )
1"
1%
#130
1$
1'
0"
0%
#140
b10 )
1"
1%
#150
0$
0'
0"
0%
#160
b11 )
1"
1%
#170
1$
1'
0"
0%
#180
b10 )
1"
1%
#190
0$
0'
0"
0%
#200
b11 )
1"
1%
#210
1$
1'
0"
0%
#220
b10 )
1"
1%
#230
0$
0'
0"
0%
#240
b11 )
1"
1%
#250
1$
1'
0"
0%
#260
b10 )
1"
1%
#270
0$
0'
0"
0%
#280
b11 )
1"
1%
#290
1$
1'
0"
0%
#300
b10 )
1"
1%
#310
0$
0'
0"
0%
#320
b11 )
1"
1%
#330
1$
1'
0"
0%
#340
b10 )
1"
1%
#350
0$
0'
0"
0%
#360
b11 )
1"
1%
#370
1$
1'
0"
0%
#380
b10 )
1"
1%
#390
0$
0'
0"
0%
#400
b11 )
1"
1%
#410
1$
1'
0"
0%
#420
b10 )
1"
1%
#430
0$
0'
0"
0%
#440
b11 )
1"
1%
#450
1$
1'
0"
0%
#460
b10 )
1"
1%
#470
0$
0'
0"
0%
#480
b11 )
1"
1%
#490
1$
1'
0"
0%
#500
b10 )
1"
1%
#510
0$
0'
0"
0%
#520
b11 )
1"
1%
#530
1$
1'
0"
0%
#540
b10 )
1"
1%
#550
0$
0'
0"
0%
#560
b11 )
1"
1%
#570
1$
1'
0"
0%
#580
b10 )
1"
1%
#590
0$
0'
0"
0%
#600
b11 )
1"
1%
#610
1$
1'
0"
0%
#620
b10 )
1"
1%
#630
0$
0'
0"
0%
#640
b11 )
1"
1%
